Metadata-Version: 2.1
Name: tosachaiprofile
Version: 0.0.1
Summary: Tosachai Profile by TcLaguna
Home-page: https://github.com/TcLaguna/TosachaiProfile
Author: TcLaguna
Author-email: tclaguna@gmail.com
License: MIT
Download-URL: https://github.com/TcLaguna/TosachaiProfile/archive/v0.0.1.zip
Keywords: Profile,Tosachai,TcLaguna
Platform: UNKNOWN
Classifier: Development Status :: 3 - Alpha
Classifier: Intended Audience :: Education
Classifier: Topic :: Utilities
Classifier: License :: OSI Approved :: MIT License
Classifier: Programming Language :: Python :: 3
Classifier: Programming Language :: Python :: 3.4
Classifier: Programming Language :: Python :: 3.5
Classifier: Programming Language :: Python :: 3.6
Classifier: Programming Language :: Python :: 3.7
Classifier: Programming Language :: Python :: 3.8
Classifier: Programming Language :: Python :: 3.9
Classifier: Programming Language :: Python :: 3.10
License-File: LICENSE.txt
